COPYING
MANIFEST.in
README.rst
bootstrap.py
buildout.cfg
setup.py
docs/conf.py
docs/index.rst
xbob/__init__.py
xbob.db.arface.egg-info/PKG-INFO
xbob.db.arface.egg-info/SOURCES.txt
xbob.db.arface.egg-info/dependency_links.txt
xbob.db.arface.egg-info/entry_points.txt
xbob.db.arface.egg-info/namespace_packages.txt
xbob.db.arface.egg-info/not-zip-safe
xbob.db.arface.egg-info/requires.txt
xbob.db.arface.egg-info/top_level.txt
xbob/db/__init__.py
xbob/db/arface/__init__.py
xbob/db/arface/create.py
xbob/db/arface/db.sql3
xbob/db/arface/driver.py
xbob/db/arface/models.py
xbob/db/arface/query.py
xbob/db/arface/test.py