Metadata-Version: 1.1
Name: xbob.db.arface
Version: 1.1.3
Summary: AR Face  Database Access API for Bob
Home-page: https://pypi.python.org/pypi/xbob.db.arface
Author: Laurent El Shafey
Author-email: laurent.el-shafey@idiap.ch
License: GPLv3
Keywords: face recognition,bob,xbob,xbob.db,AR face
Platform: UNKNOWN
Classifier: Development Status :: 5 - Production/Stable
Classifier: Environment :: Console
Classifier: Intended Audience :: Developers
Classifier: Intended Audience :: Education
Classifier: Intended Audience :: Science/Research
Classifier: License :: OSI Approved :: GNU General Public License v3 (GPLv3)
Classifier: Natural Language :: English
Classifier: Programming Language :: Python
Classifier: Programming Language :: Python :: 3
Classifier: Topic :: Scientific/Engineering :: Artificial Intelligence
Classifier: Topic :: Database :: Front-Ends
